rsm/__init__.py
rsm/api/__init__.py
rsm/api/core.py
rsm/api/integrations.py
rsm/conf/logging.conf
rsm/handlers/__init__.py
rsm/handlers/output.py
rsm/handlers/scopes.py
rsm/handlers/storage.py
rsm/mocking/ScriptResult.py
rsm/mocking/Siemplify.py
rsm/mocking/SiemplifyBase.py
rsm/mocking/SiemplifyJob.py
rsm/mocking/__init__.py
rsm/mocking/objects.py
rsm/override/__init__.py
rsm/override/rsmbase.py
rsm/override/rsmsdk.py
rsm/override/rsmutils.py
rsm/utils/__init__.py
rsm/utils/misc.py
rsm/utils/parsing.py
rsm/utils/time.py
tests/__init__.py
tests/test_misc.py
tests/test_realsiemplify.py
tests/test_time.py
rsm-1.2.9.dist-info/LICENSE.md
rsm-1.2.9.dist-info/METADATA
rsm-1.2.9.dist-info/WHEEL
rsm-1.2.9.dist-info/top_level.txt
rsm-1.2.9.dist-info/RECORD
