Metadata-Version: 2.1
Name: rsm
Version: 1.2.9
Summary: Let's simplify things for real, shall we? 
Home-page: https://github.com/antoinethebuilder/realsiemplify
Author: Antoine
Author-email: 64340767+antoinethebuilder@users.noreply.github.com
License: MIT
Platform: UNKNOWN
